lbgcli/__init__.py
lbgcli/const.py
lbgcli/main_entry.py
lbgcli/meta.py
lbgcli/module_impl.py
lbgcli/util.py
lbgcli/config/__init__.py
lbgcli/config/config.py
lbgcli/history/__init__.py
lbgcli/history/history.py
lbgcli/image/__init__.py
lbgcli/image/image.py
lbgcli/job/__init__.py
lbgcli/job/_jcc.py
lbgcli/job/job.py
lbgcli/job_group/__init__.py
lbgcli/job_group/job_group.py
lbgcli/machine/__init__.py
lbgcli/machine/machine.py
lbgcli/node/__init__.py
lbgcli/node/node.py
lbgcli/program/__init__.py
lbgcli/program/program.py
lbgcore/__init__.py
lbgcore/client.py
lbgcore/image.py
lbgcore/job.py
lbgcore/jobgroup.py
lbgcore/machine.py
lbgcore/program.py
lbgcore/server.py
lbgcore/util.py
tiefblue/__init__.py
tiefblue/client.py
lbg-1.2.29.dist-info/LICENSE
lbg-1.2.29.dist-info/METADATA
lbg-1.2.29.dist-info/WHEEL
lbg-1.2.29.dist-info/entry_points.txt
lbg-1.2.29.dist-info/top_level.txt
lbg-1.2.29.dist-info/RECORD
