Metadata-Version: 2.1
Name: lbg
Version: 1.2.29
Summary: Lebesgue Utility
Home-page: https://bohrium.dp.tech/
Author: DP Technology
Author-email: zhangzw@dp.tech
Requires-Python: >=3.7
License-File: LICENSE
Requires-Dist: oss2
Requires-Dist: requests
Requires-Dist: requests-toolbelt
Requires-Dist: aliyun-python-sdk-core
Requires-Dist: aliyun-python-sdk-kms
Requires-Dist: aliyun-python-sdk-sts
Requires-Dist: tqdm
Requires-Dist: pytimeparse
Requires-Dist: pyyaml
Requires-Dist: pandas
Requires-Dist: colorama
Requires-Dist: readchar
Requires-Dist: pyreadline
Requires-Dist: pyreadline3
Requires-Dist: validators
Requires-Dist: packaging
Requires-Dist: pyhumps
Requires-Dist: argcomplete
